mptc/__init__.py
mptc/mptc.py
mptc_Th3M4ttman-0.0.1.dist-info/LICENSE.txt
mptc_Th3M4ttman-0.0.1.dist-info/METADATA
mptc_Th3M4ttman-0.0.1.dist-info/WHEEL
mptc_Th3M4ttman-0.0.1.dist-info/top_level.txt
mptc_Th3M4ttman-0.0.1.dist-info/RECORD
