Metadata-Version: 2.1
Name: mptc-Th3M4ttman
Version: 0.0.1
Summary: a small toolkit of functions i use
Home-page: https://github.com/pypa/sampleproject
Author: Th3M4ttman
Author-email: WorkMatthewJHarros94@gmail.com
License: UNKNOWN
Platform: UNKNOWN
Classifier: Programming Language :: Python :: 3
Classifier: License :: OSI Approved :: MIT License
Classifier: Operating System :: OS Independent
Requires-Python: >=3.6
